<bbgame source="Genius sports" version="0.0.1" generated="Apr 9, 2025">
  <venue gameid="Brock-HOB" visid="Brock" visname="SUNY Brockport" homeid="HOB" homename="Hobart" date="11/16/2021" location="Bristol Gym, Geneva, NY" time="7:00 pm" attend="300" leaguegame="N" neutralgame="N" nitegame="Y" postseason="N" schednote="">
    <officials text="Brian Pullybank, Devin Maid, Kevin O'Connell"/>
    <rules prds="2" minutes="20" minutesot="5" fouls="5" qh="H"/>
  </venue>
  <status complete="Y" manualbox="Y"/>
  <team vh="V" id="Brock" code="78" name="SUNY Brockport" record="2-1,0-0 SUNYAC">
    <linescore line="30, 47" score="77">
      <lineprd prd="1" score="30"/>
      <lineprd prd="2" score="47"/>
    </linescore>
    <totals>
      <stats fgm="30" fga="68" fgm3="7" fga3="24" ftm="10" fta="13" tp="77" blk="2" stl="9" ast="19" min="200" oreb="16" dreb="32" treb="48" pf="18" tf="0" to="15" dq="0" deadball="2,2"/>
      <special vh="V" pts_to="20" pts_ch2="18" pts_paint="40" pts_fastb="10" pts_bench="30" ties="4" leads="3"/>
    </totals>
    <player uni="00" code="00" name="White,Jakai" checkname="WHITE,JAKAI" gp="1" pos="G">
      <stats fgm="0" fga="0" fgm3="0" fga3="0" ftm="0" fta="0" tp="0" blk="0" stl="0" ast="0" min="2" oreb="1" dreb="1" treb="2" pf="0" tf="0" to="0" dq="0"/>
    </player>
    <player uni="01" code="01" name="Jordan,Colby" checkname="JORDAN,COLBY" gp="0" pos="G"/>
    <player uni="02" code="02" name="James,Damario" checkname="JAMES,DAMARIO" gp="1" pos="G">
      <stats fgm="0" fga="1" fgm3="0" fga3="0" ftm="0" fta="0" tp="0" blk="0" stl="0" ast="1" min="1" oreb="0" dreb="0" treb="0" pf="0" tf="0" to="1" dq="0"/>
    </player>
    <player uni="03" code="03" name="Blyden,Thierry" checkname="BLYDEN,THIERRY" gp="0" pos="G"/>
    <player uni="04" code="04" name="Alvarez,Antonio" checkname="ALVAREZ,ANTONIO" gp="1" gs="1" pos="G">
      <stats fgm="3" fga="9" fgm3="0" fga3="5" ftm="2" fta="2" tp="8" blk="0" stl="0" ast="1" min="29" oreb="2" dreb="2" treb="4" pf="2" tf="0" to="0" dq="0"/>
    </player>
    <player uni="05" code="05" name="Hagins,Devante" checkname="HAGINS,DEVANTE" gp="1" gs="1" pos="F">
      <stats fgm="6" fga="9" fgm3="0" fga3="1" ftm="0" fta="0" tp="12" blk="0" stl="3" ast="3" min="29" oreb="3" dreb="3" treb="6" pf="3" tf="0" to="3" dq="0"/>
    </player>
    <player uni="10" code="10" name="Dobbins,Hakeem" checkname="DOBBINS,HAKEEM" gp="1" pos="G">
      <stats fgm="0" fga="1" fgm3="0" fga3="1" ftm="0" fta="0" tp="0" blk="0" stl="0" ast="0" min="3" oreb="0" dreb="0" treb="0" pf="0" tf="0" to="0" dq="0"/>
    </player>
    <player uni="11" code="11" name="Johnson,Monte" checkname="JOHNSON,MONTE" gp="1" pos="G">
      <stats fgm="4" fga="7" fgm3="1" fga3="3" ftm="0" fta="0" tp="9" blk="0" stl="0" ast="0" min="23" oreb="2" dreb="6" treb="8" pf="3" tf="0" to="4" dq="0"/>
    </player>
    <player uni="12" code="12" name="Kennedy-Gay,Brandon" checkname="KENNEDY-GAY,BRANDON" gp="1" gs="1" pos="G">
      <stats fgm="4" fga="9" fgm3="1" fga3="5" ftm="1" fta="2" tp="10" blk="0" stl="2" ast="11" min="36" oreb="0" dreb="3" treb="3" pf="3" tf="0" to="1" dq="0"/>
    </player>
    <player uni="13" code="13" name="Beckett,Mekhi" checkname="BECKETT,MEKHI" gp="1" pos="G">
      <stats fgm="6" fga="9" fgm3="5" fga3="7" ftm="2" fta="3" tp="19" blk="0" stl="1" ast="0" min="18" oreb="2" dreb="2" treb="4" pf="3" tf="0" to="1" dq="0"/>
    </player>
    <player uni="14" code="14" name="Scheve,Milo" checkname="SCHEVE,MILO" gp="1" pos="F">
      <stats fgm="1" fga="1" fgm3="0" fga3="0" ftm="0" fta="0" tp="2" blk="0" stl="0" ast="0" min="1" oreb="0" dreb="0" treb="0" pf="0" tf="0" to="0" dq="0"/>
    </player>
    <player uni="15" code="15" name="Pena,Joseph" checkname="PENA,JOSEPH" gp="1" pos="F">
      <stats fgm="0" fga="1" fgm3="0" fga3="1" ftm="0" fta="0" tp="0" blk="0" stl="0" ast="0" min="2" oreb="0" dreb="0" treb="0" pf="0" tf="0" to="0" dq="0"/>
    </player>
    <player uni="23" code="23" name="Cowie,Tyler" checkname="COWIE,TYLER" gp="1" pos="G">
      <stats fgm="0" fga="2" fgm3="0" fga3="1" ftm="0" fta="0" tp="0" blk="0" stl="0" ast="0" min="6" oreb="0" dreb="1" treb="1" pf="0" tf="0" to="0" dq="0"/>
    </player>
    <player uni="24" code="24" name="Wallace,Jahidi" checkname="WALLACE,JAHIDI" gp="1" gs="1" pos="G">
      <stats fgm="2" fga="5" fgm3="0" fga3="0" ftm="5" fta="6" tp="9" blk="1" stl="2" ast="2" min="19" oreb="0" dreb="3" treb="3" pf="3" tf="0" to="3" dq="0"/>
    </player>
    <player uni="32" code="32" name="Grady,David" checkname="GRADY,DAVID" gp="1" gs="1" pos="F">
      <stats fgm="4" fga="14" fgm3="0" fga3="0" ftm="0" fta="0" tp="8" blk="1" stl="1" ast="1" min="30" oreb="5" dreb="8" treb="13" pf="1" tf="0" to="2" dq="0"/>
    </player>
    <player uni="33" code="33" name="Jerekbo,JJ" checkname="JEREKBO,JJ" gp="1" pos="G">
      <stats fgm="0" fga="0" fgm3="0" fga3="0" ftm="0" fta="0" tp="0" blk="0" stl="0" ast="0" min="1" oreb="0" dreb="0" treb="0" pf="0" tf="0" to="0" dq="0"/>
    </player>
    <player uni="TM" code="TM" name="TEAM" checkname="TEAM" gp="1">
      <stats oreb="1" dreb="3" treb="4" pf="0" tf="0" to="0" dq="0"/>
    </player>
  </team>
  <team vh="H" id="HOB" code="282" name="Hobart" record="2-2,0-0 Liberty League">
    <linescore line="30, 23" score="53">
      <lineprd prd="1" score="30"/>
      <lineprd prd="2" score="23"/>
    </linescore>
    <totals>
      <stats fgm="17" fga="63" fgm3="7" fga3="33" ftm="12" fta="19" tp="53" blk="0" stl="9" ast="11" min="200" oreb="17" dreb="22" treb="39" pf="15" tf="0" to="18" dq="0" deadball="2,1"/>
      <special vh="H" pts_to="9" pts_ch2="14" pts_paint="14" pts_fastb="3" pts_bench="20" ties="4" leads="3"/>
    </totals>
    <player uni="01" code="01" name="Lucey,Ryan" checkname="LUCEY,RYAN" gp="1" pos="F">
      <stats fgm="1" fga="6" fgm3="0" fga3="4" ftm="0" fta="0" tp="2" blk="0" stl="0" ast="0" min="23" oreb="1" dreb="2" treb="3" pf="0" tf="0" to="2" dq="0"/>
    </player>
    <player uni="04" code="04" name="Brand,Matt" checkname="BRAND,MATT" gp="1" pos="G">
      <stats fgm="0" fga="1" fgm3="0" fga3="0" ftm="0" fta="0" tp="0" blk="0" stl="0" ast="0" min="2" oreb="0" dreb="0" treb="0" pf="0" tf="0" to="0" dq="0"/>
    </player>
    <player uni="05" code="05" name="Corrales Marco,David" checkname="CORRALES MARCO,DAVID" gp="1" pos="G">
      <stats fgm="0" fga="2" fgm3="0" fga3="1" ftm="0" fta="0" tp="0" blk="0" stl="0" ast="0" min="5" oreb="1" dreb="1" treb="2" pf="0" tf="0" to="2" dq="0"/>
    </player>
    <player uni="10" code="10" name="Lynch,Andrew" checkname="LYNCH,ANDREW" gp="1" pos="G">
      <stats fgm="3" fga="13" fgm3="3" fga3="12" ftm="0" fta="0" tp="9" blk="0" stl="1" ast="0" min="21" oreb="0" dreb="1" treb="1" pf="2" tf="0" to="2" dq="0"/>
    </player>
    <player uni="11" code="11" name="Walker,Patrick" checkname="WALKER,PATRICK" gp="1" gs="1" pos="G">
      <stats fgm="2" fga="7" fgm3="0" fga3="2" ftm="5" fta="5" tp="9" blk="0" stl="0" ast="2" min="15" oreb="2" dreb="1" treb="3" pf="4" tf="0" to="4" dq="0"/>
    </player>
    <player uni="13" code="13" name="Owenby,Chandler" checkname="OWENBY,CHANDLER" gp="1" gs="1" pos="F">
      <stats fgm="1" fga="2" fgm3="0" fga3="0" ftm="0" fta="0" tp="2" blk="0" stl="0" ast="0" min="11" oreb="0" dreb="1" treb="1" pf="1" tf="0" to="1" dq="0"/>
    </player>
    <player uni="15" code="15" name="Rajkarnikar,Avi" checkname="RAJKARNIKAR,AVI" gp="0" pos="G"/>
    <player uni="20" code="20" name="Washington,Isaiah" checkname="WASHINGTON,ISAIAH" gp="1" pos="G">
      <stats fgm="0" fga="0" fgm3="0" fga3="0" ftm="0" fta="0" tp="0" blk="0" stl="1" ast="0" min="2" oreb="0" dreb="0" treb="0" pf="1" tf="0" to="0" dq="0"/>
    </player>
    <player uni="23" code="23" name="Meshanic,Carter" checkname="MESHANIC,CARTER" gp="1" pos="G">
      <stats fgm="0" fga="1" fgm3="0" fga3="0" ftm="0" fta="0" tp="0" blk="0" stl="0" ast="0" min="5" oreb="0" dreb="0" treb="0" pf="0" tf="0" to="0" dq="0"/>
    </player>
    <player uni="24" code="24" name="Meshanic,Hunter" checkname="MESHANIC,HUNTER" gp="1" pos="F">
      <stats fgm="0" fga="1" fgm3="0" fga3="0" ftm="3" fta="4" tp="3" blk="0" stl="3" ast="1" min="14" oreb="2" dreb="0" treb="2" pf="1" tf="0" to="0" dq="0"/>
    </player>
    <player uni="25" code="25" name="Meshanic,Jackson" checkname="MESHANIC,JACKSON" gp="1" gs="1" pos="F">
      <stats fgm="5" fga="8" fgm3="3" fga3="3" ftm="2" fta="2" tp="15" blk="0" stl="1" ast="1" min="36" oreb="7" dreb="5" treb="12" pf="1" tf="0" to="1" dq="0"/>
    </player>
    <player uni="30" code="30" name="Lesure,Jack" checkname="LESURE,JACK" gp="1" gs="1" pos="G">
      <stats fgm="2" fga="5" fgm3="1" fga3="4" ftm="2" fta="5" tp="7" blk="0" stl="3" ast="2" min="25" oreb="0" dreb="5" treb="5" pf="1" tf="0" to="3" dq="0"/>
    </player>
    <player uni="31" code="31" name="Jameson,Hunter" checkname="JAMESON,HUNTER" gp="1" pos="G">
      <stats fgm="0" fga="2" fgm3="0" fga3="2" ftm="0" fta="0" tp="0" blk="0" stl="0" ast="0" min="2" oreb="0" dreb="0" treb="0" pf="0" tf="0" to="0" dq="0"/>
    </player>
    <player uni="35" code="35" name="Healy,Pat" checkname="HEALY,PAT" gp="1" pos="G">
      <stats fgm="3" fga="10" fgm3="0" fga3="2" ftm="0" fta="3" tp="6" blk="0" stl="0" ast="4" min="23" oreb="2" dreb="4" treb="6" pf="2" tf="0" to="2" dq="0"/>
    </player>
    <player uni="51" code="51" name="Rivera-Torres,Nic" checkname="RIVERA-TORRES,NIC" gp="1" pos="F">
      <stats fgm="0" fga="0" fgm3="0" fga3="0" ftm="0" fta="0" tp="0" blk="0" stl="0" ast="0" min="2" oreb="0" dreb="2" treb="2" pf="0" tf="0" to="0" dq="0"/>
    </player>
    <player uni="55" code="55" name="Rodgers,Aidan" checkname="RODGERS,AIDAN" gp="1" gs="1" pos="G">
      <stats fgm="0" fga="5" fgm3="0" fga3="3" ftm="0" fta="0" tp="0" blk="0" stl="0" ast="1" min="14" oreb="0" dreb="0" treb="0" pf="2" tf="0" to="0" dq="0"/>
    </player>
    <player uni="TM" code="TM" name="TEAM" checkname="TEAM" gp="1">
      <stats oreb="2" dreb="0" treb="2" pf="0" tf="0" to="1" dq="0"/>
    </player>
  </team>
  <plays format="tokens">
    <period number="1" time="20:00">
      <special vh="V" pts_to="12" pts_ch2="10" pts_paint="20" pts_fastb="6" pts_bench="11" ties="3" leads="2"/>
      <special vh="H" pts_to="5" pts_ch2="6" pts_paint="8" pts_fastb="2" pts_bench="13" ties="3" leads="2"/>
      <summary vh="V" fgm="12" fga="34" fgm3="2" fga3="11" ftm="4" fta="6" blk="1" stl="5" ast="8" oreb="10" dreb="13" treb="23" pf="7" tf="0" to="10"/>
      <summary vh="H" fgm="11" fga="32" fgm3="5" fga3="17" ftm="3" fta="3" blk="0" stl="4" ast="8" oreb="8" dreb="11" treb="19" pf="7" tf="0" to="11"/>
      <play vh="V" time="19:47" uni="05" team="Brock" checkname="HAGINS,DEVANTE" action="MISS" type="JUMPER" paint="Y"/>
      <play vh="H" time="19:42" uni="13" team="HOB" checkname="OWENBY,CHANDLER" action="REBOUND" type="DEF"/>
      <play vh="H" time="19:20" uni="11" team="HOB" checkname="WALKER,PATRICK" action="GOOD" type="LAYUP" paint="Y" vscore="0" hscore="2"/>
      <play vh="H" time="19:20" uni="30" team="HOB" checkname="LESURE,JACK" action="ASSIST"/>
      <play vh="V" time="19:12" uni="32" team="Brock" checkname="GRADY,DAVID" action="MISS" type="JUMPER"/>
      <play vh="V" time="19:09" uni="TM" team="Brock" checkname="TEAM" action="REBOUND" type="OFF"/>
      <play vh="V" time="19:03" uni="24" team="Brock" checkname="WALLACE,JAHIDI" action="MISS" type="JUMPER"/>
      <play vh="V" time="18:58" uni="32" team="Brock" checkname="GRADY,DAVID" action="REBOUND" type="OFF"/>
      <play vh="V" time="18:57" uni="32" team="Brock" checkname="GRADY,DAVID" action="GOOD" type="LAYUP" paint="Y" vscore="2" hscore="2"/>
      <play vh="H" time="18:48" uni="11" team="HOB" checkname="WALKER,PATRICK" action="MISS" type="LAYUP" paint="Y"/>
      <play vh="H" time="18:43" uni="25" team="HOB" checkname="MESHANIC,JACKSON" action="REBOUND" type="OFF"/>
      <play vh="H" time="18:42" uni="25" team="HOB" checkname="MESHANIC,JACKSON" action="GOOD" type="LAYUP" paint="Y" vscore="2" hscore="4"/>
      <play vh="V" time="18:33" uni="05" team="Brock" checkname="HAGINS,DEVANTE" action="FOUL"/>
      <play vh="V" time="18:33" uni="05" team="Brock" checkname="HAGINS,DEVANTE" action="TURNOVER"/>
      <play vh="H" time="18:13" uni="13" team="HOB" checkname="OWENBY,CHANDLER" action="MISS" type="LAYUP" paint="Y"/>
      <play vh="V" time="18:13" uni="24" team="Brock" checkname="WALLACE,JAHIDI" action="BLOCK"/>
      <play vh="V" time="18:06" uni="32" team="Brock" checkname="GRADY,DAVID" action="REBOUND" type="DEF"/>
      <play vh="V" time="18:04" uni="32" team="Brock" checkname="GRADY,DAVID" action="MISS" type="JUMPER"/>
      <play vh="H" time="17:53" uni="30" team="HOB" checkname="LESURE,JACK" action="REBOUND" type="DEF"/>
      <play vh="H" time="17:43" uni="13" team="HOB" checkname="OWENBY,CHANDLER" action="TURNOVER"/>
      <play vh="V" time="17:29" uni="32" team="Brock" checkname="GRADY,DAVID" action="TURNOVER"/>
      <play vh="H" time="17:29" uni="30" team="HOB" checkname="LESURE,JACK" action="STEAL"/>
      <play vh="H" time="17:20" uni="13" team="HOB" checkname="OWENBY,CHANDLER" action="GOOD" type="JUMPER" vscore="2" hscore="6"/>
      <play vh="H" time="17:20" uni="30" team="HOB" checkname="LESURE,JACK" action="ASSIST"/>
      <play vh="V" time="17:11" uni="32" team="Brock" checkname="GRADY,DAVID" action="TURNOVER"/>
      <play vh="H" time="17:02" uni="11" team="HOB" checkname="WALKER,PATRICK" action="TURNOVER"/>
      <play vh="V" time="17:02" uni="24" team="Brock" checkname="WALLACE,JAHIDI" action="STEAL"/>
      <play vh="V" time="16:48" uni="05" team="Brock" checkname="HAGINS,DEVANTE" action="GOOD" type="LAYUP" paint="Y" vscore="4" hscore="6"/>
      <play vh="V" time="16:48" uni="12" team="Brock" checkname="KENNEDY-GAY,BRANDON" action="ASSIST"/>
      <play vh="H" time="16:36" uni="25" team="HOB" checkname="MESHANIC,JACKSON" action="GOOD" type="3PTR" vscore="4" hscore="9"/>
      <play vh="H" time="16:36" uni="11" team="HOB" checkname="WALKER,PATRICK" action="ASSIST"/>
      <play vh="V" time="16:22" uni="32" team="Brock" checkname="GRADY,DAVID" action="GOOD" type="LAYUP" paint="Y" vscore="6" hscore="9"/>
      <play vh="V" time="16:22" uni="12" team="Brock" checkname="KENNEDY-GAY,BRANDON" action="ASSIST"/>
      <play vh="H" time="15:52" uni="30" team="HOB" checkname="LESURE,JACK" action="TURNOVER"/>
      <play vh="V" time="15:43" uni="24" team="Brock" checkname="WALLACE,JAHIDI" action="FOUL"/>
      <play vh="V" time="15:43" uni="24" team="Brock" checkname="WALLACE,JAHIDI" action="TURNOVER"/>
      <play vh="H" time="15:43" uni="13" team="HOB" checkname="OWENBY,CHANDLER" action="SUB" type="OUT"/>
      <play vh="H" time="15:43" uni="24" team="HOB" checkname="MESHANIC,HUNTER" action="SUB" type="IN"/>
      <play vh="V" time="15:34" uni="24" team="Brock" checkname="WALLACE,JAHIDI" action="FOUL"/>
      <play vh="V" time="15:34" uni="24" team="Brock" checkname="WALLACE,JAHIDI" action="SUB" type="OUT"/>
      <play vh="V" time="15:34" uni="11" team="Brock" checkname="JOHNSON,MONTE" action="SUB" type="IN"/>
      <play vh="H" time="15:12" uni="TM" team="HOB" checkname="TEAM" action="TURNOVER"/>
      <play vh="H" time="15:12" uni="24" team="HOB" checkname="MESHANIC,HUNTER" action="SUB" type="OUT"/>
      <play vh="H" time="15:12" uni="13" team="HOB" checkname="OWENBY,CHANDLER" action="SUB" type="IN"/>
      <play vh="V" time="15:03" uni="04" team="Brock" checkname="ALVAREZ,ANTONIO" action="MISS" type="3PTR"/>
      <play vh="V" time="14:59" uni="32" team="Brock" checkname="GRADY,DAVID" action="REBOUND" type="OFF"/>
      <play vh="V" time="14:57" uni="11" team="Brock" checkname="JOHNSON,MONTE" action="TURNOVER"/>
      <play vh="H" time="14:57" uni="13" team="HOB" checkname="OWENBY,CHANDLER" action="SUB" type="OUT"/>
      <play vh="H" time="14:57" uni="30" team="HOB" checkname="LESURE,JACK" action="SUB" type="OUT"/>
      <play vh="H" time="14:57" uni="01" team="HOB" checkname="LUCEY,RYAN" action="SUB" type="IN"/>
      <play vh="H" time="14:57" uni="24" team="HOB" checkname="MESHANIC,HUNTER" action="SUB" type="IN"/>
      <play vh="V" time="14:57" uni="05" team="Brock" checkname="HAGINS,DEVANTE" action="SUB" type="OUT"/>
      <play vh="V" time="14:57" uni="13" team="Brock" checkname="BECKETT,MEKHI" action="SUB" type="IN"/>
      <play vh="H" time="14:45" uni="11" team="HOB" checkname="WALKER,PATRICK" action="MISS" type="3PTR"/>
      <play vh="V" time="14:40" uni="04" team="Brock" checkname="ALVAREZ,ANTONIO" action="REBOUND" type="DEF"/>
      <play vh="H" time="14:22" uni="55" team="HOB" checkname="RODGERS,AIDAN" action="FOUL"/>
      <play vh="H" time="14:22" uni="55" team="HOB" checkname="RODGERS,AIDAN" action="SUB" type="OUT"/>
      <play vh="H" time="14:22" uni="35" team="HOB" checkname="HEALY,PAT" action="SUB" type="IN"/>
      <play vh="H" time="14:22" uni="11" team="HOB" checkname="WALKER,PATRICK" action="FOUL"/>
      <play vh="V" time="14:12" uni="13" team="Brock" checkname="BECKETT,MEKHI" action="MISS" type="JUMPER" paint="Y"/>
      <play vh="V" time="14:08" uni="32" team="Brock" checkname="GRADY,DAVID" action="REBOUND" type="OFF"/>
      <play vh="V" time="14:07" uni="32" team="Brock" checkname="GRADY,DAVID" action="MISS" type="JUMPER" paint="Y"/>
      <play vh="H" time="14:04" uni="01" team="HOB" checkname="LUCEY,RYAN" action="REBOUND" type="DEF"/>
      <play vh="H" time="14:00" uni="35" team="HOB" checkname="HEALY,PAT" action="MISS" type="3PTR"/>
      <play vh="H" time="13:56" uni="01" team="HOB" checkname="LUCEY,RYAN" action="REBOUND" type="OFF"/>
      <play vh="H" time="13:54" uni="01" team="HOB" checkname="LUCEY,RYAN" action="TURNOVER"/>
      <play vh="V" time="13:54" uni="13" team="Brock" checkname="BECKETT,MEKHI" action="STEAL"/>
      <play vh="V" time="13:39" uni="12" team="Brock" checkname="KENNEDY-GAY,BRANDON" action="GOOD" type="3PTR" vscore="9" hscore="9"/>
      <play vh="V" time="13:39" uni="04" team="Brock" checkname="ALVAREZ,ANTONIO" action="ASSIST"/>
      <play vh="H" time="13:19" uni="01" team="HOB" checkname="LUCEY,RYAN" action="MISS" type="3PTR"/>
      <play vh="V" time="13:13" uni="32" team="Brock" checkname="GRADY,DAVID" action="REBOUND" type="DEF"/>
      <play vh="V" time="13:09" uni="12" team="Brock" checkname="KENNEDY-GAY,BRANDON" action="TURNOVER"/>
      <play vh="H" time="13:09" uni="24" team="HOB" checkname="MESHANIC,HUNTER" action="STEAL"/>
      <play vh="H" time="12:58" uni="11" team="HOB" checkname="WALKER,PATRICK" action="TURNOVER"/>
      <play vh="H" time="12:58" uni="11" team="HOB" checkname="WALKER,PATRICK" action="SUB" type="OUT"/>
      <play vh="H" time="12:58" uni="10" team="HOB" checkname="LYNCH,ANDREW" action="SUB" type="IN"/>
      <play vh="V" time="12:58" uni="04" team="Brock" checkname="ALVAREZ,ANTONIO" action="SUB" type="OUT"/>
      <play vh="V" time="12:58" uni="32" team="Brock" checkname="GRADY,DAVID" action="SUB" type="OUT"/>
      <play vh="V" time="12:58" uni="15" team="Brock" checkname="PENA,JOSEPH" action="SUB" type="IN"/>
      <play vh="V" time="12:58" uni="23" team="Brock" checkname="COWIE,TYLER" action="SUB" type="IN"/>
      <play vh="V" time="12:35" uni="12" team="Brock" checkname="KENNEDY-GAY,BRANDON" action="GOOD" type="JUMPER" paint="Y" vscore="11" hscore="9"/>
      <play vh="H" time="12:19" uni="10" team="HOB" checkname="LYNCH,ANDREW" action="GOOD" type="3PTR" vscore="11" hscore="12"/>
      <play vh="H" time="12:19" uni="35" team="HOB" checkname="HEALY,PAT" action="ASSIST"/>
      <play vh="V" time="11:58" uni="23" team="Brock" checkname="COWIE,TYLER" action="MISS" type="JUMPER"/>
      <play vh="H" time="11:53" uni="35" team="HOB" checkname="HEALY,PAT" action="REBOUND" type="DEF"/>
      <play vh="H" time="11:49" uni="25" team="HOB" checkname="MESHANIC,JACKSON" action="GOOD" type="3PTR" vscore="11" hscore="15"/>
      <play vh="H" time="11:49" uni="35" team="HOB" checkname="HEALY,PAT" action="ASSIST"/>
      <play vh="V" time="11:33" uni="15" team="Brock" checkname="PENA,JOSEPH" action="MISS" type="3PTR"/>
      <play vh="H" time="11:29" uni="10" team="HOB" checkname="LYNCH,ANDREW" action="REBOUND" type="DEF"/>
      <play vh="H" time="11:22" uni="10" team="HOB" checkname="LYNCH,ANDREW" action="MISS" type="3PTR"/>
      <play vh="V" time="11:20" uni="TM" team="Brock" checkname="TEAM" action="REBOUND" type="DEF"/>
      <play vh="V" time="11:20" uni="12" team="Brock" checkname="KENNEDY-GAY,BRANDON" action="SUB" type="OUT"/>
      <play vh="V" time="11:20" uni="10" team="Brock" checkname="DOBBINS,HAKEEM" action="SUB" type="IN"/>
      <play vh="H" time="11:20" uni="25" team="HOB" checkname="MESHANIC,JACKSON" action="SUB" type="OUT"/>
      <play vh="H" time="11:20" uni="30" team="HOB" checkname="LESURE,JACK" action="SUB" type="IN"/>
      <play vh="V" time="11:08" uni="11" team="Brock" checkname="JOHNSON,MONTE" action="TURNOVER"/>
      <play vh="V" time="11:08" uni="15" team="Brock" checkname="PENA,JOSEPH" action="SUB" type="OUT"/>
      <play vh="V" time="11:08" uni="05" team="Brock" checkname="HAGINS,DEVANTE" action="SUB" type="IN"/>
      <play vh="H" time="10:59" uni="30" team="HOB" checkname="LESURE,JACK" action="TURNOVER"/>
      <play vh="V" time="10:59" uni="05" team="Brock" checkname="HAGINS,DEVANTE" action="STEAL"/>
      <play vh="V" time="10:37" uni="10" team="Brock" checkname="DOBBINS,HAKEEM" action="MISS" type="3PTR"/>
      <play vh="H" time="10:33" uni="30" team="HOB" checkname="LESURE,JACK" action="REBOUND" type="DEF"/>
      <play vh="H" time="10:14" uni="10" team="HOB" checkname="LYNCH,ANDREW" action="MISS" type="3PTR"/>
      <play vh="H" time="10:11" uni="35" team="HOB" checkname="HEALY,PAT" action="REBOUND" type="OFF"/>
      <play vh="H" time="10:05" uni="30" team="HOB" checkname="LESURE,JACK" action="MISS" type="3PTR"/>
      <play vh="V" time="10:01" uni="11" team="Brock" checkname="JOHNSON,MONTE" action="REBOUND" type="DEF"/>
      <play vh="H" time="09:57" uni="10" team="HOB" checkname="LYNCH,ANDREW" action="FOUL"/>
      <play vh="V" time="09:57" uni="13" team="Brock" checkname="BECKETT,MEKHI" action="GOOD" type="FT" fastb="Y" vscore="12" hscore="15"/>
      <play vh="V" time="09:57" uni="13" team="Brock" checkname="BECKETT,MEKHI" action="GOOD" type="FT" fastb="Y" vscore="13" hscore="15"/>
      <play vh="H" time="09:45" uni="35" team="HOB" checkname="HEALY,PAT" action="GOOD" type="JUMPER" vscore="13" hscore="17"/>
      <play vh="H" time="09:45" uni="24" team="HOB" checkname="MESHANIC,HUNTER" action="ASSIST"/>
      <play vh="V" time="09:34" uni="13" team="Brock" checkname="BECKETT,MEKHI" action="MISS" type="3PTR"/>
      <play vh="H" time="09:31" uni="35" team="HOB" checkname="HEALY,PAT" action="REBOUND" type="DEF"/>
      <play vh="H" time="09:16" uni="10" team="HOB" checkname="LYNCH,ANDREW" action="MISS" type="3PTR"/>
      <play vh="H" time="09:13" uni="24" team="HOB" checkname="MESHANIC,HUNTER" action="REBOUND" type="OFF"/>
      <play vh="V" time="09:13" uni="11" team="Brock" checkname="JOHNSON,MONTE" action="FOUL"/>
      <play vh="H" time="09:13" uni="24" team="HOB" checkname="MESHANIC,HUNTER" action="GOOD" type="FT" vscore="13" hscore="18"/>
      <play vh="V" time="09:13" uni="13" team="Brock" checkname="BECKETT,MEKHI" action="SUB" type="OUT"/>
      <play vh="V" time="09:13" uni="23" team="Brock" checkname="COWIE,TYLER" action="SUB" type="OUT"/>
      <play vh="V" time="09:13" uni="04" team="Brock" checkname="ALVAREZ,ANTONIO" action="SUB" type="IN"/>
      <play vh="V" time="09:13" uni="32" team="Brock" checkname="GRADY,DAVID" action="SUB" type="IN"/>
      <play vh="H" time="09:13" uni="24" team="HOB" checkname="MESHANIC,HUNTER" action="GOOD" type="FT" vscore="13" hscore="19"/>
      <play vh="H" time="09:13" uni="24" team="HOB" checkname="MESHANIC,HUNTER" action="SUB" type="OUT"/>
      <play vh="H" time="09:13" uni="25" team="HOB" checkname="MESHANIC,JACKSON" action="SUB" type="IN"/>
      <play vh="V" time="09:02" uni="05" team="Brock" checkname="HAGINS,DEVANTE" action="MISS" type="JUMPER"/>
      <play vh="V" time="08:58" uni="32" team="Brock" checkname="GRADY,DAVID" action="REBOUND" type="OFF"/>
      <play vh="V" time="08:57" uni="11" team="Brock" checkname="JOHNSON,MONTE" action="GOOD" type="LAYUP" paint="Y" vscore="15" hscore="19"/>
      <play vh="V" time="08:57" uni="32" team="Brock" checkname="GRADY,DAVID" action="ASSIST"/>
      <play vh="H" time="08:44" uni="10" team="HOB" checkname="LYNCH,ANDREW" action="GOOD" type="3PTR" vscore="15" hscore="22"/>
      <play vh="H" time="08:44" uni="25" team="HOB" checkname="MESHANIC,JACKSON" action="ASSIST"/>
      <play vh="V" time="08:27" uni="04" team="Brock" checkname="ALVAREZ,ANTONIO" action="MISS" type="3PTR"/>
      <play vh="H" time="08:23" uni="35" team="HOB" checkname="HEALY,PAT" action="REBOUND" type="DEF"/>
      <play vh="H" time="08:18" uni="01" team="HOB" checkname="LUCEY,RYAN" action="MISS" type="3PTR"/>
      <play vh="H" time="08:14" uni="35" team="HOB" checkname="HEALY,PAT" action="REBOUND" type="OFF"/>
      <play vh="H" time="08:12" uni="35" team="HOB" checkname="HEALY,PAT" action="MISS" type="LAYUP" paint="Y"/>
      <play vh="V" time="08:10" uni="05" team="Brock" checkname="HAGINS,DEVANTE" action="REBOUND" type="DEF"/>
      <play vh="V" time="08:06" uni="04" team="Brock" checkname="ALVAREZ,ANTONIO" action="GOOD" type="LAYUP" paint="Y" fastb="Y" vscore="17" hscore="22"/>
      <play vh="V" time="08:06" uni="05" team="Brock" checkname="HAGINS,DEVANTE" action="ASSIST"/>
      <play vh="V" time="08:06" uni="TM" team="Brock" checkname="TEAM" action="TIMEOUT" type="30SEC"/>
      <play vh="H" time="08:06" uni="30" team="HOB" checkname="LESURE,JACK" action="SUB" type="OUT"/>
      <play vh="H" time="08:06" uni="55" team="HOB" checkname="RODGERS,AIDAN" action="SUB" type="IN"/>
      <play vh="V" time="08:06" uni="10" team="Brock" checkname="DOBBINS,HAKEEM" action="SUB" type="OUT"/>
      <play vh="V" time="08:06" uni="12" team="Brock" checkname="KENNEDY-GAY,BRANDON" action="SUB" type="IN"/>
      <play vh="H" time="07:36" uni="10" team="HOB" checkname="LYNCH,ANDREW" action="GOOD" type="3PTR" vscore="17" hscore="25"/>
      <play vh="H" time="07:36" uni="35" team="HOB" checkname="HEALY,PAT" action="ASSIST"/>
      <play vh="V" time="07:25" uni="04" team="Brock" checkname="ALVAREZ,ANTONIO" action="MISS" type="3PTR"/>
      <play vh="H" time="07:22" uni="TM" team="HOB" checkname="TEAM" action="REBOUND" type="DEADB"/>
      <play vh="V" time="07:22" uni="12" team="Brock" checkname="KENNEDY-GAY,BRANDON" action="FOUL"/>
      <play vh="H" time="07:00" uni="55" team="HOB" checkname="RODGERS,AIDAN" action="MISS" type="JUMPER"/>
      <play vh="V" time="06:57" uni="32" team="Brock" checkname="GRADY,DAVID" action="REBOUND" type="DEF"/>
      <play vh="V" time="06:55" uni="32" team="Brock" checkname="GRADY,DAVID" action="MISS" type="JUMPER" paint="Y"/>
      <play vh="V" time="06:50" uni="05" team="Brock" checkname="HAGINS,DEVANTE" action="REBOUND" type="OFF"/>
      <play vh="V" time="06:49" uni="32" team="Brock" checkname="GRADY,DAVID" action="MISS" type="DUNK" paint="Y"/>
      <play vh="V" time="06:45" uni="11" team="Brock" checkname="JOHNSON,MONTE" action="REBOUND" type="OFF"/>
      <play vh="V" time="06:28" uni="11" team="Brock" checkname="JOHNSON,MONTE" action="GOOD" type="LAYUP" paint="Y" vscore="19" hscore="25"/>
      <play vh="V" time="06:28" uni="12" team="Brock" checkname="KENNEDY-GAY,BRANDON" action="ASSIST"/>
      <play vh="H" time="06:07" uni="35" team="HOB" checkname="HEALY,PAT" action="MISS" type="LAYUP" paint="Y"/>
      <play vh="H" time="06:05" uni="TM" team="HOB" checkname="TEAM" action="REBOUND" type="OFF"/>
      <play vh="H" time="06:05" uni="10" team="HOB" checkname="LYNCH,ANDREW" action="SUB" type="OUT"/>
      <play vh="H" time="06:05" uni="35" team="HOB" checkname="HEALY,PAT" action="SUB" type="OUT"/>
      <play vh="H" time="06:05" uni="11" team="HOB" checkname="WALKER,PATRICK" action="SUB" type="IN"/>
      <play vh="H" time="06:05" uni="30" team="HOB" checkname="LESURE,JACK" action="SUB" type="IN"/>
      <play vh="H" time="06:03" uni="11" team="HOB" checkname="WALKER,PATRICK" action="TURNOVER"/>
      <play vh="V" time="06:03" uni="05" team="Brock" checkname="HAGINS,DEVANTE" action="STEAL"/>
      <play vh="V" time="05:54" uni="32" team="Brock" checkname="GRADY,DAVID" action="MISS" type="LAYUP" paint="Y"/>
      <play vh="V" time="05:51" uni="11" team="Brock" checkname="JOHNSON,MONTE" action="REBOUND" type="OFF"/>
      <play vh="V" time="05:50" uni="11" team="Brock" checkname="JOHNSON,MONTE" action="MISS" type="LAYUP" paint="Y"/>
      <play vh="H" time="05:47" uni="25" team="HOB" checkname="MESHANIC,JACKSON" action="REBOUND" type="DEF"/>
      <play vh="H" time="05:43" uni="11" team="HOB" checkname="WALKER,PATRICK" action="MISS" type="3PTR"/>
      <play vh="V" time="05:39" uni="32" team="Brock" checkname="GRADY,DAVID" action="REBOUND" type="DEF"/>
      <play vh="H" time="05:32" uni="55" team="HOB" checkname="RODGERS,AIDAN" action="FOUL"/>
      <play vh="H" time="05:32" uni="55" team="HOB" checkname="RODGERS,AIDAN" action="SUB" type="OUT"/>
      <play vh="H" time="05:32" uni="05" team="HOB" checkname="CORRALES MARCO,DAVID" action="SUB" type="IN"/>
      <play vh="V" time="05:32" uni="11" team="Brock" checkname="JOHNSON,MONTE" action="SUB" type="OUT"/>
      <play vh="V" time="05:32" uni="24" team="Brock" checkname="WALLACE,JAHIDI" action="SUB" type="IN"/>
      <play vh="V" time="05:12" uni="04" team="Brock" checkname="ALVAREZ,ANTONIO" action="MISS" type="3PTR"/>
      <play vh="V" time="05:08" uni="05" team="Brock" checkname="HAGINS,DEVANTE" action="REBOUND" type="OFF"/>
      <play vh="V" time="05:08" uni="05" team="Brock" checkname="HAGINS,DEVANTE" action="GOOD" type="LAYUP" paint="Y" vscore="21" hscore="25"/>
      <play vh="H" time="05:08" uni="TM" team="HOB" checkname="TEAM" action="TIMEOUT" type="30SEC"/>
      <play vh="H" time="05:08" uni="01" team="HOB" checkname="LUCEY,RYAN" action="SUB" type="OUT"/>
      <play vh="H" time="05:08" uni="13" team="HOB" checkname="OWENBY,CHANDLER" action="SUB" type="IN"/>
      <play vh="H" time="04:58" uni="05" team="HOB" checkname="CORRALES MARCO,DAVID" action="MISS" type="3PTR"/>
      <play vh="V" time="04:55" uni="24" team="Brock" checkname="WALLACE,JAHIDI" action="REBOUND" type="DEF"/>
      <play vh="H" time="04:50" uni="13" team="HOB" checkname="OWENBY,CHANDLER" action="FOUL"/>
      <play vh="V" time="04:50" uni="24" team="Brock" checkname="WALLACE,JAHIDI" action="MISS" type="FT" fastb="Y"/>
      <play vh="V" time="04:50" uni="TM" team="Brock" checkname="TEAM" action="REBOUND" type="DEADB"/>
      <play vh="V" time="04:50" uni="24" team="Brock" checkname="WALLACE,JAHIDI" action="GOOD" type="FT" fastb="Y" vscore="22" hscore="25"/>
      <play vh="H" time="04:38" uni="30" team="HOB" checkname="LESURE,JACK" action="TURNOVER"/>
      <play vh="H" time="04:37" uni="11" team="HOB" checkname="WALKER,PATRICK" action="SUB" type="OUT"/>
      <play vh="H" time="04:37" uni="10" team="HOB" checkname="LYNCH,ANDREW" action="SUB" type="IN"/>
      <play vh="V" time="04:22" uni="05" team="Brock" checkname="HAGINS,DEVANTE" action="GOOD" type="DUNK" paint="Y" vscore="24" hscore="25"/>
      <play vh="H" time="04:02" uni="10" team="HOB" checkname="LYNCH,ANDREW" action="MISS" type="3PTR"/>
      <play vh="V" time="03:55" uni="12" team="Brock" checkname="KENNEDY-GAY,BRANDON" action="REBOUND" type="DEF"/>
      <play vh="V" time="03:54" uni="24" team="Brock" checkname="WALLACE,JAHIDI" action="MISS" type="JUMPER"/>
      <play vh="H" time="03:50" uni="05" team="HOB" checkname="CORRALES MARCO,DAVID" action="REBOUND" type="DEF"/>
      <play vh="H" time="03:39" uni="05" team="HOB" checkname="CORRALES MARCO,DAVID" action="TURNOVER"/>
      <play vh="V" time="03:39" uni="12" team="Brock" checkname="KENNEDY-GAY,BRANDON" action="STEAL"/>
      <play vh="V" time="03:34" uni="05" team="Brock" checkname="HAGINS,DEVANTE" action="MISS" type="3PTR"/>
      <play vh="H" time="03:30" uni="25" team="HOB" checkname="MESHANIC,JACKSON" action="REBOUND" type="DEF"/>
      <play vh="H" time="03:11" uni="10" team="HOB" checkname="LYNCH,ANDREW" action="MISS" type="3PTR"/>
      <play vh="H" time="03:06" uni="05" team="HOB" checkname="CORRALES MARCO,DAVID" action="REBOUND" type="OFF"/>
      <play vh="H" time="02:55" uni="05" team="HOB" checkname="CORRALES MARCO,DAVID" action="MISS" type="LAYUP" paint="Y"/>
      <play vh="H" time="02:51" uni="25" team="HOB" checkname="MESHANIC,JACKSON" action="REBOUND" type="OFF"/>
      <play vh="H" time="02:51" uni="25" team="HOB" checkname="MESHANIC,JACKSON" action="GOOD" type="LAYUP" paint="Y" vscore="24" hscore="27"/>
      <play vh="V" time="02:32" uni="24" team="Brock" checkname="WALLACE,JAHIDI" action="TURNOVER"/>
      <play vh="H" time="02:32" uni="30" team="HOB" checkname="LESURE,JACK" action="STEAL"/>
      <play vh="H" time="02:29" uni="30" team="HOB" checkname="LESURE,JACK" action="GOOD" type="LAYUP" paint="Y" fastb="Y" vscore="24" hscore="29"/>
      <play vh="V" time="02:29" uni="24" team="Brock" checkname="WALLACE,JAHIDI" action="SUB" type="OUT"/>
      <play vh="V" time="02:29" uni="13" team="Brock" checkname="BECKETT,MEKHI" action="SUB" type="IN"/>
      <play vh="V" time="02:29" uni="24" team="Brock" checkname="WALLACE,JAHIDI" action="FOUL"/>
      <play vh="H" time="02:29" uni="30" team="HOB" checkname="LESURE,JACK" action="GOOD" type="FT" vscore="24" hscore="30"/>
      <play vh="H" time="02:21" uni="35" team="HOB" checkname="HEALY,PAT" action="FOUL"/>
      <play vh="H" time="02:21" uni="05" team="HOB" checkname="CORRALES MARCO,DAVID" action="SUB" type="OUT"/>
      <play vh="H" time="02:21" uni="35" team="HOB" checkname="HEALY,PAT" action="SUB" type="IN"/>
      <play vh="V" time="02:21" uni="12" team="Brock" checkname="KENNEDY-GAY,BRANDON" action="MISS" type="FT" fastb="Y"/>
      <play vh="V" time="02:21" uni="TM" team="Brock" checkname="TEAM" action="REBOUND" type="DEADB"/>
      <play vh="V" time="02:21" uni="12" team="Brock" checkname="KENNEDY-GAY,BRANDON" action="GOOD" type="FT" fastb="Y" vscore="25" hscore="30"/>
      <play vh="V" time="02:21" uni="04" team="Brock" checkname="ALVAREZ,ANTONIO" action="SUB" type="OUT"/>
      <play vh="V" time="02:21" uni="11" team="Brock" checkname="JOHNSON,MONTE" action="SUB" type="IN"/>
      <play vh="H" time="02:06" uni="35" team="HOB" checkname="HEALY,PAT" action="MISS" type="LAYUP" paint="Y"/>
      <play vh="V" time="02:03" uni="11" team="Brock" checkname="JOHNSON,MONTE" action="REBOUND" type="DEF"/>
      <play vh="V" time="01:46" uni="11" team="Brock" checkname="JOHNSON,MONTE" action="MISS" type="3PTR"/>
      <play vh="V" time="01:42" uni="13" team="Brock" checkname="BECKETT,MEKHI" action="REBOUND" type="OFF"/>
      <play vh="V" time="01:37" uni="11" team="Brock" checkname="JOHNSON,MONTE" action="GOOD" type="LAYUP" paint="Y" vscore="27" hscore="30"/>
      <play vh="V" time="01:37" uni="12" team="Brock" checkname="KENNEDY-GAY,BRANDON" action="ASSIST"/>
      <play vh="H" time="01:22" uni="10" team="HOB" checkname="LYNCH,ANDREW" action="FOUL"/>
      <play vh="H" time="01:22" uni="10" team="HOB" checkname="LYNCH,ANDREW" action="TURNOVER"/>
      <play vh="H" time="01:22" uni="10" team="HOB" checkname="LYNCH,ANDREW" action="SUB" type="OUT"/>
      <play vh="H" time="01:22" uni="13" team="HOB" checkname="OWENBY,CHANDLER" action="SUB" type="OUT"/>
      <play vh="H" time="01:22" uni="01" team="HOB" checkname="LUCEY,RYAN" action="SUB" type="IN"/>
      <play vh="H" time="01:22" uni="24" team="HOB" checkname="MESHANIC,HUNTER" action="SUB" type="IN"/>
      <play vh="V" time="01:06" uni="13" team="Brock" checkname="BECKETT,MEKHI" action="GOOD" type="3PTR" vscore="30" hscore="30"/>
      <play vh="V" time="01:06" uni="05" team="Brock" checkname="HAGINS,DEVANTE" action="ASSIST"/>
      <play vh="H" time="00:35" uni="35" team="HOB" checkname="HEALY,PAT" action="MISS" type="JUMPER"/>
      <play vh="V" time="00:30" uni="12" team="Brock" checkname="KENNEDY-GAY,BRANDON" action="REBOUND" type="DEF"/>
      <play vh="V" time="00:28" uni="13" team="Brock" checkname="BECKETT,MEKHI" action="TURNOVER"/>
      <play vh="H" time="00:28" uni="24" team="HOB" checkname="MESHANIC,HUNTER" action="STEAL"/>
      <play vh="H" time="00:09" uni="35" team="HOB" checkname="HEALY,PAT" action="MISS" type="JUMPER"/>
      <play vh="V" time="00:06" uni="13" team="Brock" checkname="BECKETT,MEKHI" action="REBOUND" type="DEF"/>
      <play vh="V" time="00:03" uni="11" team="Brock" checkname="JOHNSON,MONTE" action="FOUL"/>
      <play vh="V" time="00:03" uni="11" team="Brock" checkname="JOHNSON,MONTE" action="TURNOVER"/>
      <clock time="00:00"/>
    </period>
    <period number="2" time="20:00">
      <special vh="V" pts_to="8" pts_ch2="8" pts_paint="20" pts_fastb="4" pts_bench="19" ties="1" leads="1"/>
      <special vh="H" pts_to="4" pts_ch2="8" pts_paint="6" pts_fastb="1" pts_bench="7" ties="1" leads="1"/>
      <summary vh="V" fgm="18" fga="34" fgm3="5" fga3="13" ftm="6" fta="7" blk="1" stl="4" ast="11" oreb="6" dreb="19" treb="25" pf="11" tf="0" to="5"/>
      <summary vh="H" fgm="6" fga="31" fgm3="2" fga3="16" ftm="9" fta="16" blk="0" stl="5" ast="3" oreb="9" dreb="11" treb="20" pf="8" tf="0" to="7"/>
      <play vh="V" time="20:00" uni="13" team="Brock" checkname="BECKETT,MEKHI" action="SUB" type="OUT"/>
      <play vh="V" time="20:00" uni="04" team="Brock" checkname="ALVAREZ,ANTONIO" action="SUB" type="IN"/>
      <play vh="H" time="20:00" uni="01" team="HOB" checkname="LUCEY,RYAN" action="SUB" type="OUT"/>
      <play vh="H" time="20:00" uni="24" team="HOB" checkname="MESHANIC,HUNTER" action="SUB" type="OUT"/>
      <play vh="H" time="20:00" uni="35" team="HOB" checkname="HEALY,PAT" action="SUB" type="OUT"/>
      <play vh="H" time="20:00" uni="11" team="HOB" checkname="WALKER,PATRICK" action="SUB" type="IN"/>
      <play vh="H" time="20:00" uni="13" team="HOB" checkname="OWENBY,CHANDLER" action="SUB" type="IN"/>
      <play vh="H" time="20:00" uni="55" team="HOB" checkname="RODGERS,AIDAN" action="SUB" type="IN"/>
      <play vh="H" time="19:45" uni="11" team="HOB" checkname="WALKER,PATRICK" action="MISS" type="LAYUP" paint="Y"/>
      <play vh="V" time="19:42" uni="11" team="Brock" checkname="JOHNSON,MONTE" action="REBOUND" type="DEF"/>
      <play vh="V" time="19:39" uni="05" team="Brock" checkname="HAGINS,DEVANTE" action="GOOD" type="LAYUP" paint="Y" fastb="Y" vscore="32" hscore="30"/>
      <play vh="V" time="19:39" uni="12" team="Brock" checkname="KENNEDY-GAY,BRANDON" action="ASSIST"/>
      <play vh="H" time="19:28" uni="55" team="HOB" checkname="RODGERS,AIDAN" action="MISS" type="3PTR"/>
      <play vh="H" time="19:24" uni="11" team="HOB" checkname="WALKER,PATRICK" action="REBOUND" type="OFF"/>
      <play vh="H" time="19:21" uni="11" team="HOB" checkname="WALKER,PATRICK" action="TURNOVER"/>
      <play vh="V" time="19:21" uni="05" team="Brock" checkname="HAGINS,DEVANTE" action="STEAL"/>
      <play vh="V" time="19:14" uni="11" team="Brock" checkname="JOHNSON,MONTE" action="MISS" type="3PTR"/>
      <play vh="V" time="19:10" uni="05" team="Brock" checkname="HAGINS,DEVANTE" action="REBOUND" type="OFF"/>
      <play vh="V" time="19:07" uni="05" team="Brock" checkname="HAGINS,DEVANTE" action="GOOD" type="JUMPER" paint="Y" vscore="34" hscore="30"/>
      <play vh="H" time="18:43" uni="55" team="HOB" checkname="RODGERS,AIDAN" action="MISS" type="3PTR"/>
      <play vh="V" time="18:41" uni="TM" team="Brock" checkname="TEAM" action="REBOUND" type="DEADB"/>
      <play vh="H" time="18:41" uni="11" team="HOB" checkname="WALKER,PATRICK" action="FOUL"/>
      <play vh="H" time="18:41" uni="11" team="HOB" checkname="WALKER,PATRICK" action="SUB" type="OUT"/>
      <play vh="H" time="18:41" uni="10" team="HOB" checkname="LYNCH,ANDREW" action="SUB" type="IN"/>
      <play vh="V" time="18:23" uni="32" team="Brock" checkname="GRADY,DAVID" action="GOOD" type="DUNK" paint="Y" vscore="36" hscore="30"/>
      <play vh="V" time="18:23" uni="12" team="Brock" checkname="KENNEDY-GAY,BRANDON" action="ASSIST"/>
      <play vh="H" time="18:17" uni="TM" team="HOB" checkname="TEAM" action="TIMEOUT" type="TEAM"/>
      <play vh="H" time="17:52" uni="55" team="HOB" checkname="RODGERS,AIDAN" action="MISS" type="JUMPER"/>
      <play vh="V" time="17:49" uni="11" team="Brock" checkname="JOHNSON,MONTE" action="REBOUND" type="DEF"/>
      <play vh="V" time="17:46" uni="11" team="Brock" checkname="JOHNSON,MONTE" action="TURNOVER"/>
      <play vh="H" time="17:46" uni="30" team="HOB" checkname="LESURE,JACK" action="STEAL"/>
      <play vh="H" time="17:31" uni="25" team="HOB" checkname="MESHANIC,JACKSON" action="MISS" type="JUMPER" paint="Y"/>
      <play vh="V" time="17:28" uni="32" team="Brock" checkname="GRADY,DAVID" action="REBOUND" type="DEF"/>
      <play vh="V" time="17:14" uni="32" team="Brock" checkname="GRADY,DAVID" action="MISS" type="JUMPER" paint="Y"/>
      <play vh="H" time="17:11" uni="25" team="HOB" checkname="MESHANIC,JACKSON" action="REBOUND" type="DEF"/>
      <play vh="H" time="17:09" uni="10" team="HOB" checkname="LYNCH,ANDREW" action="TURNOVER"/>
      <play vh="H" time="17:09" uni="13" team="HOB" checkname="OWENBY,CHANDLER" action="SUB" type="OUT"/>
      <play vh="H" time="17:09" uni="24" team="HOB" checkname="MESHANIC,HUNTER" action="SUB" type="IN"/>
      <play vh="V" time="16:58" uni="12" team="Brock" checkname="KENNEDY-GAY,BRANDON" action="GOOD" type="LAYUP" paint="Y" vscore="38" hscore="30"/>
      <play vh="H" time="16:34" uni="30" team="HOB" checkname="LESURE,JACK" action="MISS" type="3PTR"/>
      <play vh="V" time="16:31" uni="05" team="Brock" checkname="HAGINS,DEVANTE" action="REBOUND" type="DEF"/>
      <play vh="V" time="16:25" uni="12" team="Brock" checkname="KENNEDY-GAY,BRANDON" action="MISS" type="3PTR"/>
      <play vh="H" time="16:21" uni="30" team="HOB" checkname="LESURE,JACK" action="REBOUND" type="DEF"/>
      <play vh="H" time="16:07" uni="10" team="HOB" checkname="LYNCH,ANDREW" action="MISS" type="3PTR"/>
      <play vh="H" time="16:04" uni="25" team="HOB" checkname="MESHANIC,JACKSON" action="REBOUND" type="OFF"/>
      <play vh="H" time="15:58" uni="30" team="HOB" checkname="LESURE,JACK" action="GOOD" type="3PTR" vscore="38" hscore="33"/>
      <play vh="H" time="15:58" uni="55" team="HOB" checkname="RODGERS,AIDAN" action="ASSIST"/>
      <play vh="V" time="15:30" uni="32" team="Brock" checkname="GRADY,DAVID" action="MISS" type="LAYUP" paint="Y"/>
      <play vh="H" time="15:28" uni="30" team="HOB" checkname="LESURE,JACK" action="REBOUND" type="DEF"/>
      <play vh="H" time="15:22" uni="10" team="HOB" checkname="LYNCH,ANDREW" action="MISS" type="LAYUP" paint="Y"/>
      <play vh="H" time="15:22" uni="24" team="HOB" checkname="MESHANIC,HUNTER" action="REBOUND" type="OFF"/>
      <play vh="V" time="15:22" uni="12" team="Brock" checkname="KENNEDY-GAY,BRANDON" action="FOUL"/>
      <play vh="H" time="15:22" uni="24" team="HOB" checkname="MESHANIC,HUNTER" action="GOOD" type="FT" fastb="Y" vscore="38" hscore="34"/>
      <play vh="H" time="15:22" uni="24" team="HOB" checkname="MESHANIC,HUNTER" action="MISS" type="FT" fastb="Y"/>
      <play vh="V" time="15:20" uni="11" team="Brock" checkname="JOHNSON,MONTE" action="REBOUND" type="DEF"/>
      <play vh="V" time="15:12" uni="32" team="Brock" checkname="GRADY,DAVID" action="GOOD" type="JUMPER" paint="Y" vscore="40" hscore="34"/>
      <play vh="H" time="15:04" uni="25" team="HOB" checkname="MESHANIC,JACKSON" action="TURNOVER"/>
      <play vh="V" time="14:52" uni="04" team="Brock" checkname="ALVAREZ,ANTONIO" action="MISS" type="JUMPER" paint="Y"/>
      <play vh="H" time="14:49" uni="25" team="HOB" checkname="MESHANIC,JACKSON" action="REBOUND" type="DEF"/>
      <play vh="H" time="14:39" uni="30" team="HOB" checkname="LESURE,JACK" action="MISS" type="3PTR"/>
      <play vh="V" time="14:37" uni="32" team="Brock" checkname="GRADY,DAVID" action="REBOUND" type="DEF"/>
      <play vh="H" time="14:37" uni="24" team="HOB" checkname="MESHANIC,HUNTER" action="FOUL"/>
      <play vh="V" time="14:37" uni="04" team="Brock" checkname="ALVAREZ,ANTONIO" action="SUB" type="OUT"/>
      <play vh="V" time="14:37" uni="32" team="Brock" checkname="GRADY,DAVID" action="SUB" type="OUT"/>
      <play vh="V" time="14:37" uni="13" team="Brock" checkname="BECKETT,MEKHI" action="SUB" type="IN"/>
      <play vh="V" time="14:37" uni="24" team="Brock" checkname="WALLACE,JAHIDI" action="SUB" type="IN"/>
      <play vh="V" time="14:23" uni="13" team="Brock" checkname="BECKETT,MEKHI" action="GOOD" type="3PTR" vscore="43" hscore="34"/>
      <play vh="V" time="14:23" uni="12" team="Brock" checkname="KENNEDY-GAY,BRANDON" action="ASSIST"/>
      <play vh="H" time="14:05" uni="55" team="HOB" checkname="RODGERS,AIDAN" action="MISS" type="3PTR"/>
      <play vh="V" time="14:02" uni="TM" team="Brock" checkname="TEAM" action="REBOUND" type="DEF"/>
      <play vh="H" time="14:02" uni="30" team="HOB" checkname="LESURE,JACK" action="SUB" type="OUT"/>
      <play vh="H" time="14:02" uni="55" team="HOB" checkname="RODGERS,AIDAN" action="SUB" type="OUT"/>
      <play vh="H" time="14:02" uni="01" team="HOB" checkname="LUCEY,RYAN" action="SUB" type="IN"/>
      <play vh="H" time="14:02" uni="35" team="HOB" checkname="HEALY,PAT" action="SUB" type="IN"/>
      <play vh="V" time="13:44" uni="12" team="Brock" checkname="KENNEDY-GAY,BRANDON" action="GOOD" type="JUMPER" vscore="45" hscore="34"/>
      <play vh="H" time="13:29" uni="10" team="HOB" checkname="LYNCH,ANDREW" action="MISS" type="3PTR"/>
      <play vh="V" time="13:27" uni="11" team="Brock" checkname="JOHNSON,MONTE" action="FOUL"/>
      <play vh="H" time="13:26" uni="TM" team="HOB" checkname="TEAM" action="REBOUND" type="OFF"/>
      <play vh="H" time="13:25" uni="10" team="HOB" checkname="LYNCH,ANDREW" action="MISS" type="3PTR"/>
      <play vh="V" time="13:22" uni="05" team="Brock" checkname="HAGINS,DEVANTE" action="REBOUND" type="DEF"/>
      <play vh="V" time="13:18" uni="05" team="Brock" checkname="HAGINS,DEVANTE" action="TURNOVER"/>
      <play vh="H" time="13:18" uni="24" team="HOB" checkname="MESHANIC,HUNTER" action="STEAL"/>
      <play vh="H" time="13:03" uni="24" team="HOB" checkname="MESHANIC,HUNTER" action="MISS" type="LAYUP" paint="Y"/>
      <play vh="H" time="12:59" uni="25" team="HOB" checkname="MESHANIC,JACKSON" action="REBOUND" type="OFF"/>
      <play vh="H" time="12:59" uni="25" team="HOB" checkname="MESHANIC,JACKSON" action="MISS" type="LAYUP" paint="Y"/>
      <play vh="H" time="12:58" uni="25" team="HOB" checkname="MESHANIC,JACKSON" action="REBOUND" type="OFF"/>
      <play vh="V" time="12:58" uni="13" team="Brock" checkname="BECKETT,MEKHI" action="FOUL"/>
      <play vh="H" time="12:58" uni="25" team="HOB" checkname="MESHANIC,JACKSON" action="GOOD" type="FT" vscore="45" hscore="35"/>
      <play vh="V" time="12:58" uni="11" team="Brock" checkname="JOHNSON,MONTE" action="SUB" type="OUT"/>
      <play vh="V" time="12:58" uni="04" team="Brock" checkname="ALVAREZ,ANTONIO" action="SUB" type="IN"/>
      <play vh="H" time="12:58" uni="25" team="HOB" checkname="MESHANIC,JACKSON" action="GOOD" type="FT" vscore="45" hscore="36"/>
      <play vh="V" time="12:33" uni="13" team="Brock" checkname="BECKETT,MEKHI" action="GOOD" type="3PTR" vscore="48" hscore="36"/>
      <play vh="V" time="12:33" uni="24" team="Brock" checkname="WALLACE,JAHIDI" action="ASSIST"/>
      <play vh="H" time="12:24" uni="01" team="HOB" checkname="LUCEY,RYAN" action="GOOD" type="LAYUP" paint="Y" vscore="48" hscore="38"/>
      <play vh="H" time="12:24" uni="TM" team="HOB" checkname="TEAM" action="TIMEOUT" type="30SEC"/>
      <play vh="V" time="12:24" uni="24" team="Brock" checkname="WALLACE,JAHIDI" action="SUB" type="OUT"/>
      <play vh="V" time="12:24" uni="32" team="Brock" checkname="GRADY,DAVID" action="SUB" type="IN"/>
      <play vh="H" time="12:11" uni="25" team="HOB" checkname="MESHANIC,JACKSON" action="FOUL"/>
      <play vh="H" time="12:11" uni="10" team="HOB" checkname="LYNCH,ANDREW" action="SUB" type="OUT"/>
      <play vh="H" time="12:11" uni="23" team="HOB" checkname="MESHANIC,CARTER" action="SUB" type="IN"/>
      <play vh="V" time="12:00" uni="05" team="Brock" checkname="HAGINS,DEVANTE" action="TURNOVER"/>
      <play vh="H" time="12:00" uni="25" team="HOB" checkname="MESHANIC,JACKSON" action="STEAL"/>
      <play vh="H" time="11:45" uni="35" team="HOB" checkname="HEALY,PAT" action="GOOD" type="LAYUP" paint="Y" vscore="48" hscore="40"/>
      <play vh="V" time="11:38" uni="13" team="Brock" checkname="BECKETT,MEKHI" action="MISS" type="3PTR"/>
      <play vh="V" time="11:33" uni="04" team="Brock" checkname="ALVAREZ,ANTONIO" action="REBOUND" type="OFF"/>
      <play vh="V" time="11:31" uni="04" team="Brock" checkname="ALVAREZ,ANTONIO" action="GOOD" type="LAYUP" paint="Y" vscore="50" hscore="40"/>
      <play vh="H" time="11:22" uni="23" team="HOB" checkname="MESHANIC,CARTER" action="MISS" type="LAYUP" paint="Y"/>
      <play vh="V" time="11:22" uni="32" team="Brock" checkname="GRADY,DAVID" action="BLOCK"/>
      <play vh="V" time="11:20" uni="TM" team="Brock" checkname="TEAM" action="REBOUND" type="DEF"/>
      <play vh="V" time="11:11" uni="05" team="Brock" checkname="HAGINS,DEVANTE" action="GOOD" type="LAYUP" paint="Y" vscore="52" hscore="40"/>
      <play vh="V" time="11:11" uni="12" team="Brock" checkname="KENNEDY-GAY,BRANDON" action="ASSIST"/>
      <play vh="H" time="10:56" uni="35" team="HOB" checkname="HEALY,PAT" action="MISS" type="3PTR"/>
      <play vh="V" time="10:54" uni="TM" team="Brock" checkname="TEAM" action="REBOUND" type="DEADB"/>
      <play vh="H" time="10:54" uni="24" team="HOB" checkname="MESHANIC,HUNTER" action="SUB" type="OUT"/>
      <play vh="H" time="10:54" uni="11" team="HOB" checkname="WALKER,PATRICK" action="SUB" type="IN"/>
      <play vh="V" time="10:42" uni="32" team="Brock" checkname="GRADY,DAVID" action="MISS" type="JUMPER"/>
      <play vh="H" time="10:36" uni="35" team="HOB" checkname="HEALY,PAT" action="REBOUND" type="DEF"/>
      <play vh="H" time="10:35" uni="01" team="HOB" checkname="LUCEY,RYAN" action="MISS" type="3PTR"/>
      <play vh="H" time="10:32" uni="11" team="HOB" checkname="WALKER,PATRICK" action="REBOUND" type="OFF"/>
      <play vh="V" time="10:32" uni="13" team="Brock" checkname="BECKETT,MEKHI" action="FOUL"/>
      <play vh="H" time="10:32" uni="11" team="HOB" checkname="WALKER,PATRICK" action="GOOD" type="FT" vscore="52" hscore="41"/>
      <play vh="H" time="10:32" uni="11" team="HOB" checkname="WALKER,PATRICK" action="GOOD" type="FT" vscore="52" hscore="42"/>
      <play vh="V" time="10:16" uni="12" team="Brock" checkname="KENNEDY-GAY,BRANDON" action="MISS" type="3PTR"/>
      <play vh="H" time="10:12" uni="01" team="HOB" checkname="LUCEY,RYAN" action="REBOUND" type="DEF"/>
      <play vh="V" time="10:00" uni="13" team="Brock" checkname="BECKETT,MEKHI" action="FOUL"/>
      <play vh="V" time="10:00" uni="04" team="Brock" checkname="ALVAREZ,ANTONIO" action="SUB" type="OUT"/>
      <play vh="V" time="10:00" uni="13" team="Brock" checkname="BECKETT,MEKHI" action="SUB" type="OUT"/>
      <play vh="V" time="10:00" uni="11" team="Brock" checkname="JOHNSON,MONTE" action="SUB" type="IN"/>
      <play vh="V" time="10:00" uni="24" team="Brock" checkname="WALLACE,JAHIDI" action="SUB" type="IN"/>
      <play vh="H" time="09:52" uni="35" team="HOB" checkname="HEALY,PAT" action="GOOD" type="JUMPER" vscore="52" hscore="44"/>
      <play vh="V" time="09:29" uni="11" team="Brock" checkname="JOHNSON,MONTE" action="GOOD" type="3PTR" vscore="55" hscore="44"/>
      <play vh="V" time="09:29" uni="12" team="Brock" checkname="KENNEDY-GAY,BRANDON" action="ASSIST"/>
      <play vh="H" time="09:09" uni="25" team="HOB" checkname="MESHANIC,JACKSON" action="GOOD" type="3PTR" vscore="55" hscore="47"/>
      <play vh="H" time="09:09" uni="11" team="HOB" checkname="WALKER,PATRICK" action="ASSIST"/>
      <play vh="V" time="08:47" uni="12" team="Brock" checkname="KENNEDY-GAY,BRANDON" action="MISS" type="LAYUP" paint="Y"/>
      <play vh="V" time="08:42" uni="32" team="Brock" checkname="GRADY,DAVID" action="REBOUND" type="OFF"/>
      <play vh="V" time="08:41" uni="32" team="Brock" checkname="GRADY,DAVID" action="MISS" type="LAYUP" paint="Y"/>
      <play vh="H" time="08:38" uni="25" team="HOB" checkname="MESHANIC,JACKSON" action="REBOUND" type="DEF"/>
      <play vh="H" time="08:21" uni="11" team="HOB" checkname="WALKER,PATRICK" action="MISS" type="LAYUP" paint="Y"/>
      <play vh="H" time="08:18" uni="25" team="HOB" checkname="MESHANIC,JACKSON" action="REBOUND" type="OFF"/>
      <play vh="H" time="08:17" uni="01" team="HOB" checkname="LUCEY,RYAN" action="TURNOVER"/>
      <play vh="V" time="08:17" uni="12" team="Brock" checkname="KENNEDY-GAY,BRANDON" action="STEAL"/>
      <play vh="V" time="08:13" uni="TM" team="Brock" checkname="TEAM" action="TIMEOUT" type="TEAM"/>
      <play vh="V" time="08:00" uni="12" team="Brock" checkname="KENNEDY-GAY,BRANDON" action="MISS" type="3PTR"/>
      <play vh="H" time="07:56" uni="11" team="HOB" checkname="WALKER,PATRICK" action="REBOUND" type="DEF"/>
      <play vh="H" time="07:49" uni="01" team="HOB" checkname="LUCEY,RYAN" action="MISS" type="LAYUP" paint="Y"/>
      <play vh="V" time="07:46" uni="11" team="Brock" checkname="JOHNSON,MONTE" action="REBOUND" type="DEF"/>
      <play vh="V" time="07:41" uni="24" team="Brock" checkname="WALLACE,JAHIDI" action="GOOD" type="LAYUP" paint="Y" fastb="Y" vscore="57" hscore="47"/>
      <play vh="V" time="07:41" uni="05" team="Brock" checkname="HAGINS,DEVANTE" action="ASSIST"/>
      <play vh="H" time="07:25" uni="11" team="HOB" checkname="WALKER,PATRICK" action="GOOD" type="LAYUP" paint="Y" vscore="57" hscore="49"/>
      <play vh="H" time="07:25" uni="35" team="HOB" checkname="HEALY,PAT" action="ASSIST"/>
      <play vh="V" time="07:25" uni="05" team="Brock" checkname="HAGINS,DEVANTE" action="FOUL"/>
      <play vh="V" time="07:25" uni="32" team="Brock" checkname="GRADY,DAVID" action="SUB" type="OUT"/>
      <play vh="V" time="07:25" uni="04" team="Brock" checkname="ALVAREZ,ANTONIO" action="SUB" type="IN"/>
      <play vh="H" time="07:25" uni="11" team="HOB" checkname="WALKER,PATRICK" action="GOOD" type="FT" vscore="57" hscore="50"/>
      <play vh="H" time="07:04" uni="11" team="HOB" checkname="WALKER,PATRICK" action="FOUL"/>
      <play vh="V" time="07:04" uni="24" team="Brock" checkname="WALLACE,JAHIDI" action="GOOD" type="FT" vscore="58" hscore="50"/>
      <play vh="V" time="07:04" uni="24" team="Brock" checkname="WALLACE,JAHIDI" action="GOOD" type="FT" vscore="59" hscore="50"/>
      <play vh="V" time="06:52" uni="05" team="Brock" checkname="HAGINS,DEVANTE" action="FOUL"/>
      <play vh="H" time="06:52" uni="11" team="HOB" checkname="WALKER,PATRICK" action="GOOD" type="FT" vscore="59" hscore="51"/>
      <play vh="H" time="06:52" uni="23" team="HOB" checkname="MESHANIC,CARTER" action="SUB" type="OUT"/>
      <play vh="H" time="06:52" uni="30" team="HOB" checkname="LESURE,JACK" action="SUB" type="IN"/>
      <play vh="V" time="06:52" uni="05" team="Brock" checkname="HAGINS,DEVANTE" action="SUB" type="OUT"/>
      <play vh="V" time="06:52" uni="13" team="Brock" checkname="BECKETT,MEKHI" action="SUB" type="IN"/>
      <play vh="H" time="06:52" uni="11" team="HOB" checkname="WALKER,PATRICK" action="GOOD" type="FT" vscore="59" hscore="52"/>
      <play vh="V" time="06:27" uni="12" team="Brock" checkname="KENNEDY-GAY,BRANDON" action="MISS" type="3PTR"/>
      <play vh="V" time="06:22" uni="13" team="Brock" checkname="BECKETT,MEKHI" action="REBOUND" type="OFF"/>
      <play vh="H" time="06:14" uni="11" team="HOB" checkname="WALKER,PATRICK" action="FOUL"/>
      <play vh="V" time="06:14" uni="24" team="Brock" checkname="WALLACE,JAHIDI" action="GOOD" type="FT" vscore="60" hscore="52"/>
      <play vh="H" time="06:14" uni="11" team="HOB" checkname="WALKER,PATRICK" action="SUB" type="OUT"/>
      <play vh="H" time="06:14" uni="10" team="HOB" checkname="LYNCH,ANDREW" action="SUB" type="IN"/>
      <play vh="V" time="06:14" uni="24" team="Brock" checkname="WALLACE,JAHIDI" action="GOOD" type="FT" vscore="61" hscore="52"/>
      <play vh="V" time="05:56" uni="04" team="Brock" checkname="ALVAREZ,ANTONIO" action="FOUL"/>
      <play vh="H" time="05:56" uni="30" team="HOB" checkname="LESURE,JACK" action="GOOD" type="FT" vscore="61" hscore="53"/>
      <play vh="H" time="05:56" uni="30" team="HOB" checkname="LESURE,JACK" action="MISS" type="FT"/>
      <play vh="V" time="05:56" uni="24" team="Brock" checkname="WALLACE,JAHIDI" action="REBOUND" type="DEF"/>
      <play vh="H" time="05:47" uni="30" team="HOB" checkname="LESURE,JACK" action="FOUL"/>
      <play vh="V" time="05:47" uni="11" team="Brock" checkname="JOHNSON,MONTE" action="SUB" type="OUT"/>
      <play vh="V" time="05:47" uni="32" team="Brock" checkname="GRADY,DAVID" action="SUB" type="IN"/>
      <play vh="V" time="05:38" uni="24" team="Brock" checkname="WALLACE,JAHIDI" action="TURNOVER"/>
      <play vh="H" time="05:38" uni="10" team="HOB" checkname="LYNCH,ANDREW" action="STEAL"/>
      <play vh="H" time="05:19" uni="01" team="HOB" checkname="LUCEY,RYAN" action="MISS" type="3PTR"/>
      <play vh="H" time="05:16" uni="25" team="HOB" checkname="MESHANIC,JACKSON" action="REBOUND" type="OFF"/>
      <play vh="H" time="05:14" uni="25" team="HOB" checkname="MESHANIC,JACKSON" action="MISS" type="LAYUP" paint="Y"/>
      <play vh="V" time="05:11" uni="04" team="Brock" checkname="ALVAREZ,ANTONIO" action="REBOUND" type="DEF"/>
      <play vh="V" time="05:07" uni="13" team="Brock" checkname="BECKETT,MEKHI" action="GOOD" type="3PTR" vscore="64" hscore="53"/>
      <play vh="V" time="05:07" uni="12" team="Brock" checkname="KENNEDY-GAY,BRANDON" action="ASSIST"/>
      <play vh="H" time="04:57" uni="10" team="HOB" checkname="LYNCH,ANDREW" action="MISS" type="3PTR"/>
      <play vh="V" time="04:53" uni="24" team="Brock" checkname="WALLACE,JAHIDI" action="REBOUND" type="DEF"/>
      <play vh="V" time="04:36" uni="13" team="Brock" checkname="BECKETT,MEKHI" action="GOOD" type="3PTR" vscore="67" hscore="53"/>
      <play vh="V" time="04:36" uni="12" team="Brock" checkname="KENNEDY-GAY,BRANDON" action="ASSIST"/>
      <play vh="V" time="04:18" uni="12" team="Brock" checkname="KENNEDY-GAY,BRANDON" action="FOUL"/>
      <play vh="H" time="04:18" uni="35" team="HOB" checkname="HEALY,PAT" action="MISS" type="FT"/>
      <play vh="V" time="04:15" uni="32" team="Brock" checkname="GRADY,DAVID" action="REBOUND" type="DEF"/>
      <play vh="V" time="03:55" uni="24" team="Brock" checkname="WALLACE,JAHIDI" action="GOOD" type="JUMPER" vscore="69" hscore="53"/>
      <play vh="H" time="03:48" uni="TM" team="HOB" checkname="TEAM" action="TIMEOUT" type="TEAM"/>
      <play vh="V" time="03:37" uni="04" team="Brock" checkname="ALVAREZ,ANTONIO" action="FOUL"/>
      <play vh="H" time="03:37" uni="35" team="HOB" checkname="HEALY,PAT" action="MISS" type="FT"/>
      <play vh="H" time="03:37" uni="TM" team="HOB" checkname="TEAM" action="REBOUND" type="DEADB"/>
      <play vh="H" time="03:37" uni="35" team="HOB" checkname="HEALY,PAT" action="MISS" type="FT"/>
      <play vh="V" time="03:35" uni="32" team="Brock" checkname="GRADY,DAVID" action="REBOUND" type="DEF"/>
      <play vh="V" time="03:14" uni="24" team="Brock" checkname="WALLACE,JAHIDI" action="MISS" type="JUMPER" paint="Y"/>
      <play vh="V" time="03:10" uni="04" team="Brock" checkname="ALVAREZ,ANTONIO" action="REBOUND" type="OFF"/>
      <play vh="H" time="03:10" uni="35" team="HOB" checkname="HEALY,PAT" action="FOUL"/>
      <play vh="V" time="03:10" uni="04" team="Brock" checkname="ALVAREZ,ANTONIO" action="GOOD" type="FT" vscore="70" hscore="53"/>
      <play vh="V" time="03:10" uni="04" team="Brock" checkname="ALVAREZ,ANTONIO" action="GOOD" type="FT" vscore="71" hscore="53"/>
      <play vh="H" time="03:03" uni="35" team="HOB" checkname="HEALY,PAT" action="TURNOVER"/>
      <play vh="V" time="03:03" uni="32" team="Brock" checkname="GRADY,DAVID" action="STEAL"/>
      <play vh="V" time="02:49" uni="04" team="Brock" checkname="ALVAREZ,ANTONIO" action="MISS" type="3PTR"/>
      <play vh="H" time="02:46" uni="30" team="HOB" checkname="LESURE,JACK" action="REBOUND" type="DEF"/>
      <play vh="V" time="02:46" uni="32" team="Brock" checkname="GRADY,DAVID" action="FOUL"/>
      <play vh="H" time="02:46" uni="30" team="HOB" checkname="LESURE,JACK" action="MISS" type="FT"/>
      <play vh="H" time="02:46" uni="TM" team="HOB" checkname="TEAM" action="REBOUND" type="DEADB"/>
      <play vh="H" time="02:46" uni="30" team="HOB" checkname="LESURE,JACK" action="MISS" type="FT"/>
      <play vh="V" time="02:46" uni="12" team="Brock" checkname="KENNEDY-GAY,BRANDON" action="REBOUND" type="DEF"/>
      <play vh="V" time="02:39" uni="TM" team="Brock" checkname="TEAM" action="TIMEOUT" type="30SEC"/>
      <play vh="V" time="02:20" uni="04" team="Brock" checkname="ALVAREZ,ANTONIO" action="GOOD" type="JUMPER" vscore="73" hscore="53"/>
      <play vh="H" time="02:09" uni="35" team="HOB" checkname="HEALY,PAT" action="TURNOVER"/>
      <play vh="V" time="02:09" uni="24" team="Brock" checkname="WALLACE,JAHIDI" action="STEAL"/>
      <play vh="H" time="01:58" uni="01" team="HOB" checkname="LUCEY,RYAN" action="SUB" type="OUT"/>
      <play vh="H" time="01:58" uni="10" team="HOB" checkname="LYNCH,ANDREW" action="SUB" type="OUT"/>
      <play vh="H" time="01:58" uni="25" team="HOB" checkname="MESHANIC,JACKSON" action="SUB" type="OUT"/>
      <play vh="H" time="01:58" uni="30" team="HOB" checkname="LESURE,JACK" action="SUB" type="OUT"/>
      <play vh="H" time="01:58" uni="35" team="HOB" checkname="HEALY,PAT" action="SUB" type="OUT"/>
      <play vh="H" time="01:58" uni="04" team="HOB" checkname="BRAND,MATT" action="SUB" type="IN"/>
      <play vh="H" time="01:58" uni="05" team="HOB" checkname="CORRALES MARCO,DAVID" action="SUB" type="IN"/>
      <play vh="H" time="01:58" uni="20" team="HOB" checkname="WASHINGTON,ISAIAH" action="SUB" type="IN"/>
      <play vh="H" time="01:58" uni="31" team="HOB" checkname="JAMESON,HUNTER" action="SUB" type="IN"/>
      <play vh="H" time="01:58" uni="51" team="HOB" checkname="RIVERA-TORRES,NIC" action="SUB" type="IN"/>
      <play vh="V" time="01:52" uni="13" team="Brock" checkname="BECKETT,MEKHI" action="GOOD" type="JUMPER" paint="Y" vscore="75" hscore="53"/>
      <play vh="V" time="01:52" uni="24" team="Brock" checkname="WALLACE,JAHIDI" action="ASSIST"/>
      <play vh="H" time="01:52" uni="20" team="HOB" checkname="WASHINGTON,ISAIAH" action="FOUL"/>
      <play vh="V" time="01:52" uni="32" team="Brock" checkname="GRADY,DAVID" action="SUB" type="OUT"/>
      <play vh="V" time="01:52" uni="23" team="Brock" checkname="COWIE,TYLER" action="SUB" type="IN"/>
      <play vh="V" time="01:52" uni="13" team="Brock" checkname="BECKETT,MEKHI" action="MISS" type="FT"/>
      <play vh="H" time="01:52" uni="51" team="HOB" checkname="RIVERA-TORRES,NIC" action="REBOUND" type="DEF"/>
      <play vh="H" time="01:37" uni="04" team="HOB" checkname="BRAND,MATT" action="MISS" type="JUMPER"/>
      <play vh="V" time="01:33" uni="13" team="Brock" checkname="BECKETT,MEKHI" action="REBOUND" type="DEF"/>
      <play vh="V" time="01:29" uni="TM" team="Brock" checkname="TEAM" action="TIMEOUT" type="TEAM"/>
      <play vh="V" time="01:29" uni="12" team="Brock" checkname="KENNEDY-GAY,BRANDON" action="SUB" type="OUT"/>
      <play vh="V" time="01:29" uni="13" team="Brock" checkname="BECKETT,MEKHI" action="SUB" type="OUT"/>
      <play vh="V" time="01:29" uni="24" team="Brock" checkname="WALLACE,JAHIDI" action="SUB" type="OUT"/>
      <play vh="V" time="01:29" uni="00" team="Brock" checkname="WHITE,JAKAI" action="SUB" type="IN"/>
      <play vh="V" time="01:29" uni="02" team="Brock" checkname="JAMES,DAMARIO" action="SUB" type="IN"/>
      <play vh="V" time="01:29" uni="14" team="Brock" checkname="SCHEVE,MILO" action="SUB" type="IN"/>
      <play vh="V" time="01:16" uni="23" team="Brock" checkname="COWIE,TYLER" action="MISS" type="3PTR"/>
      <play vh="V" time="01:10" uni="00" team="Brock" checkname="WHITE,JAKAI" action="REBOUND" type="OFF"/>
      <play vh="V" time="01:02" uni="02" team="Brock" checkname="JAMES,DAMARIO" action="MISS" type="JUMPER"/>
      <play vh="H" time="00:57" uni="51" team="HOB" checkname="RIVERA-TORRES,NIC" action="REBOUND" type="DEF"/>
      <play vh="H" time="00:50" uni="31" team="HOB" checkname="JAMESON,HUNTER" action="MISS" type="3PTR"/>
      <play vh="V" time="00:46" uni="00" team="Brock" checkname="WHITE,JAKAI" action="REBOUND" type="DEF"/>
      <play vh="V" time="00:44" uni="TM" team="Brock" checkname="TEAM" action="TIMEOUT" type="30SEC"/>
      <play vh="V" time="00:44" uni="04" team="Brock" checkname="ALVAREZ,ANTONIO" action="SUB" type="OUT"/>
      <play vh="V" time="00:44" uni="33" team="Brock" checkname="JEREKBO,JJ" action="SUB" type="IN"/>
      <play vh="V" time="00:31" uni="02" team="Brock" checkname="JAMES,DAMARIO" action="TURNOVER"/>
      <play vh="H" time="00:31" uni="20" team="HOB" checkname="WASHINGTON,ISAIAH" action="STEAL"/>
      <play vh="H" time="00:27" uni="05" team="HOB" checkname="CORRALES MARCO,DAVID" action="TURNOVER"/>
      <play vh="V" time="00:10" uni="14" team="Brock" checkname="SCHEVE,MILO" action="GOOD" type="LAYUP" paint="Y" vscore="77" hscore="53"/>
      <play vh="V" time="00:10" uni="02" team="Brock" checkname="JAMES,DAMARIO" action="ASSIST"/>
      <play vh="H" time="00:07" uni="31" team="HOB" checkname="JAMESON,HUNTER" action="MISS" type="3PTR"/>
      <play vh="V" time="00:02" uni="23" team="Brock" checkname="COWIE,TYLER" action="REBOUND" type="DEF"/>
      <clock time="00:00"/>
    </period>
  </plays>
</bbgame>